{
    "Settings": {
        "type": "C",
        "class": "\\IPS\\Settings"
    },
    "ipsLog": {
        "type": "C",
        "class": "\\IPS\\Log"
    },
    "Request": {
        "type": "C",
        "class": "\\IPS\\Request"
    },
    "coreFrontGlobalTheme": {
        "type": "S",
        "class": "\\IPS\\Theme\\class_core_front_global"
    },
    "SandboxedTemplate": {
        "type": "C",
        "class": "\\IPS\\Theme\\SandboxedTemplate"
    },
    "coreGlobalGlobalTheme": {
        "type": "S",
        "class": "\\IPS\\Theme\\class_core_global_global"
    },
    "BuilderIterator": {
        "type": "C",
        "class": "\\IPS\\Application\\BuilderIterator"
    },
    "BuilderFilter": {
        "type": "C",
        "class": "\\IPS\\Application\\BuilderFilter"
    },
    "developer": {
        "type": "C",
        "class": "\\IPS\\core\\modules\\admin\\applications\\developer"
    },
    "MultiRedirect": {
        "type": "C",
        "class": "\\IPS\\Helpers\\MultipleRedirect"
    },
    "Theme": {
        "type": "C",
        "class": "\\IPS\\Theme"
    },
    "Db": {
        "type": "C",
        "class": "\\IPS\\Db"
    },
    "Application": {
        "type": "C",
        "class": "\\IPS\\Application"
    },
    "Output": {
        "type": "C",
        "class": "\\IPS\\Output"
    },
    "Dispatcher": {
        "type": "C",
        "class": "\\IPS\\Dispatcher"
    },
    "moduleApplications": {
        "type": "C",
        "class": "\\IPS\\core\\modules\\admin\\applications\\applications"
    },
    "adminGlobal": {
        "type": "S",
        "class": "\\IPS\\Theme\\class_core_admin_global"
    },
    "DataStore": {
        "type": "C",
        "class": "\\IPS\\Data\\Store"
    },
    "Hooks": {
        "type": "C",
        "class": "\\IPS\\Plugin\\Hook"
    }
}